zawolib/__init__.py
zawolib/msgcount.py
zawolib/progressbar.py
zawolib/example/__init__.py
zawolib/example/example.py
zawolib-1.0.1.dist-info/METADATA
zawolib-1.0.1.dist-info/WHEEL
zawolib-1.0.1.dist-info/top_level.txt
zawolib-1.0.1.dist-info/RECORD
