Metadata-Version: 2.1
Name: zawolib
Version: 1.0.1
Summary: zawolib typu zawolib
Author: zawodev
Author-email: chuj@cieto.obchodzi.pl
Keywords: python,video,stream,video stream,camera stream,sockets
Classifier: Development Status :: 1 - Planning
Classifier: Intended Audience :: Developers
Classifier: Programming Language :: Python :: 3
Classifier: Operating System :: Unix
Classifier: Operating System :: MacOS :: MacOS X
Classifier: Operating System :: Microsoft :: Windows
Requires-Dist: discord
